backbone/__init__.py
backbone/action.py
backbone/environment.py
afrl-0.0.1.4.dist-info/METADATA
afrl-0.0.1.4.dist-info/WHEEL
afrl-0.0.1.4.dist-info/top_level.txt
afrl-0.0.1.4.dist-info/RECORD
