Metadata-Version: 2.1
Name: afrl
Version: 0.0.1.4
Summary: All Forms of Reinforcement Learning
Home-page: https://gitlab.com/alessandro.flati/afrl
Author: Alessandro Flati
Requires-Dist: numpy ~=1.26.0
